vsi/__init__.py
vsi/recorder.py
vsi/trainer.py
vsi/version.py
vsi/vsi.py
vbsoundinference-1.1.0.dist-info/METADATA
vbsoundinference-1.1.0.dist-info/WHEEL
vbsoundinference-1.1.0.dist-info/top_level.txt
vbsoundinference-1.1.0.dist-info/RECORD
