Metadata-Version: 2.4
Name: vbsoundinference
Version: 1.1.0
Summary: A python library for wake-word detection on low end devices.
Author: Samarth Javagal
Author-email: samarthjavagal@gmail.com
Classifier: Programming Language :: Python :: 3
Classifier: License :: OSI Approved :: MIT License
Classifier: Operating System :: OS Independent
Requires-Python: >=3.6
Requires-Dist: numpy
Requires-Dist: sounddevice
Requires-Dist: torch
Dynamic: author
Dynamic: author-email
Dynamic: classifier
Dynamic: description
Dynamic: description-content-type
Dynamic: requires-dist
Dynamic: requires-python
Dynamic: summary
